modland_client.py
modland_client-0.22.dist-info/entry_points.txt
modland_client-0.22.dist-info/WHEEL
modland_client-0.22.dist-info/METADATA
modland_client-0.22.dist-info/RECORD
