Metadata-Version: 2.1
Name: modland_client
Version: 0.22
Summary: Modland tracker music archive client working via ftp
Author-email: Andrew Lobanov <spline1986@yandex.ru>
Requires-Python: >=3.5
Classifier: Programming Language :: Python :: 3
Classifier: License :: OSI Approved :: GNU General Public License v3 (GPLv3)
Classifier: Operating System :: POSIX
Project-URL: Bug Tracker, https://codeberg.org/spline/modland_client/issues
Project-URL: Homepage, https://codeberg.org/spline/modland_client
